genetables/__init__.py
genetables/filereader.py
genetables/gff.py
genetables/gtbed.py
genetables/nucleotides.py
genetables/reader.py
genetables-0.1.1.data/scripts/famap
genetables-0.1.1.data/scripts/gffspace
genetables-0.1.1.data/scripts/ntxtab
genetables-0.1.1.data/scripts/rnafolder
genetables-0.1.1.data/scripts/tadlads
genetables-0.1.1.dist-info/DESCRIPTION.rst
genetables-0.1.1.dist-info/METADATA
genetables-0.1.1.dist-info/RECORD
genetables-0.1.1.dist-info/WHEEL
genetables-0.1.1.dist-info/metadata.json
genetables-0.1.1.dist-info/top_level.txt
