Metadata-Version: 2.0
Name: genetables
Version: 0.1.1
Summary: Genome table processing
Home-page: https://github.com/setempler/genetables.py
Author: Sven E. Templer
Author-email: sven.templer@gmail.com
License: MIT
Keywords: genomics,bioinformatics,sequencing
Platform: UNKNOWN
Classifier: License :: OSI Approved :: MIT License
Classifier: Programming Language :: Python :: 2.7
